pypura/__init__.py
pypura/const.py
pypura/exceptions.py
pypura/pura.py
pypura/py.typed
pypura/utils.py
pypura/ws_subscriber.py
pypura-2.1.1.dist-info/METADATA
pypura-2.1.1.dist-info/WHEEL
pypura-2.1.1.dist-info/licenses/LICENSE
pypura-2.1.1.dist-info/RECORD
