Metadata-Version: 2.4
Name: pypura
Version: 2.1.1
Summary: Python package for interacting with Pura smart fragrance diffuser
License-Expression: MIT
License-File: LICENSE
Author: Nathan Spencer
Author-email: natekspencer@gmail.com
Requires-Python: >=3.10
Classifier: Programming Language :: Python :: 3
Classifier: Programming Language :: Python :: 3.10
Classifier: Programming Language :: Python :: 3.11
Classifier: Programming Language :: Python :: 3.12
Classifier: Programming Language :: Python :: 3.13
Classifier: Programming Language :: Python :: 3.14
Requires-Dist: aiohttp (>=3.12.15)
Requires-Dist: boto3 (>=1.28)
Requires-Dist: pycognito (>=2024.2.0)
